[
  {
    "type": "O+",
    "state": "Nivel suficiente",
    "date": "2023-01-15T22:15:16.661Z"
  },
  {
    "type": "A+",
    "state": "Nivel suficiente",
    "date": "2023-01-15T22:15:16.661Z"
  },
  {
    "type": "B+",
    "state": "Nivel suficiente",
    "date": "2023-01-15T22:15:16.661Z"
  },
  {
    "type": "AB+",
    "state": "Nivel suficiente",
    "date": "2023-01-15T22:15:16.661Z"
  },
  {
    "type": "O-",
    "state": "Nivel critico",
    "date": "2023-01-15T22:15:16.661Z"
  },
  {
    "type": "A-",
    "state": "Nivel bajo",
    "date": "2023-01-15T22:15:16.661Z"
  },
  {
    "type": "B-",
    "state": "Nivel critico",
    "date": "2023-01-15T22:15:16.661Z"
  },
  {
    "type": "AB-",
    "state": "Nivel suficiente",
    "date": "2023-01-15T22:15:16.661Z"
  }
]